setup.py
open_edx_class_export.egg-info/PKG-INFO
open_edx_class_export.egg-info/SOURCES.txt
open_edx_class_export.egg-info/dependency_links.txt
open_edx_class_export.egg-info/requires.txt
open_edx_class_export.egg-info/top_level.txt
src/__init__.py
src/exportClass.py
src/testExportClass.py
src/tornado/__init__.py
src/tornado/auth.py
src/tornado/autoreload.py
src/tornado/curl_httpclient.py
src/tornado/database.py
src/tornado/escape.py
src/tornado/gen.py
src/tornado/httpclient.py
src/tornado/httpserver.py
src/tornado/httputil.py
src/tornado/ioloop.py
src/tornado/iostream.py
src/tornado/locale.py
src/tornado/netutil.py
src/tornado/options.py
src/tornado/process.py
src/tornado/simple_httpclient.py
src/tornado/stack_context.py
src/tornado/template.py
src/tornado/testing.py
src/tornado/util.py
src/tornado/web.py
src/tornado/websocket.py
src/tornado/wsgi.py
src/tornado/platform/__init__.py
src/tornado/platform/auto.py
src/tornado/platform/common.py
src/tornado/platform/interface.py
src/tornado/platform/posix.py
src/tornado/platform/twisted.py
src/tornado/platform/windows.py
src/tornado/test/__init__.py
src/tornado/test/auth_test.py
src/tornado/test/curl_httpclient_test.py
src/tornado/test/escape_test.py
src/tornado/test/gen_test.py
src/tornado/test/httpclient_test.py
src/tornado/test/httpserver_test.py
src/tornado/test/httputil_test.py
src/tornado/test/import_test.py
src/tornado/test/ioloop_test.py
src/tornado/test/iostream_test.py
src/tornado/test/options_test.py
src/tornado/test/process_test.py
src/tornado/test/run_pyversion_tests.py
src/tornado/test/runtests.py
src/tornado/test/simple_httpclient_test.py
src/tornado/test/stack_context_test.py
src/tornado/test/template_test.py
src/tornado/test/testing_test.py
src/tornado/test/twisted_test.py
src/tornado/test/util_test.py
src/tornado/test/web_test.py
src/tornado/test/wsgi_test.py