Metadata-Version: 1.0
Name: open-edx-class-export
Version: 0.20
Summary: In an OpenEdX instance installation, produces class statistics from event stream data.
Home-page: https://github.com/paepcke/open_edx_class_export
Author: Andreas Paepcke
Author-email: UNKNOWN
License: BSD
Keywords: openEdX,instruction
Platform: UNKNOWN
